nailgun/__init__.py
nailgun/client.py
nailgun/config.py
nailgun/entities.py
nailgun/entity_fields.py
nailgun/entity_mixins.py
nailgun/signals.py
nailgun-0.32.0.dist-info/LICENSE
nailgun-0.32.0.dist-info/METADATA
nailgun-0.32.0.dist-info/WHEEL
nailgun-0.32.0.dist-info/top_level.txt
nailgun-0.32.0.dist-info/RECORD
